<?xml version="1.0"?>
<EmbeddedProfile xmlns:xsi="http://www.w3.org/2001/XMLSchema-instance" xmlns:xsd="http://www.w3.org/2001/XMLSchema">
  <ToolchainID>com.sysprogs.toolchains.nongnu.armcc</ToolchainID>
  <ToolchainVersion>
    <GCC>5.x</GCC>
    <Revision>1</Revision>
  </ToolchainVersion>
  <BspID>KEIL:Keil/STM32F1xx_DFP</BspID>
  <BspVersion>2.3.0</BspVersion>
  <McuID>STM32F103ZE</McuID>
  <MCUDefinitionFile>SVD/STM32F103xx.svd</MCUDefinitionFile>
  <MCUProperties>
    <Entries />
  </MCUProperties>
  <BSPSourceFolderName>Device-specific files</BSPSourceFolderName>
  <MCUMakFile>mcu.mak</MCUMakFile>
  <ReferencedFrameworks />
  <FrameworkProperties>
    <Entries />
  </FrameworkProperties>
  <TestFrameworkProperties>
    <Entries />
  </TestFrameworkProperties>
  <ImportedProject>
    <ImporterID>com.sysprogs.project_importers.keil</ImporterID>
    <RelativeProjectPath>..\..\..\Experiment_47_2Serial_IAP_RTC_FLASH_APP\USER\RTC.uvprojx</RelativeProjectPath>
    <AllDependencies>
      <ProjectDependency>
        <RelativePath>..\..\..\Experiment_47_2Serial_IAP_RTC_FLASH_APP\USER\RTC.uvprojx</RelativePath>
        <Timestamp>132230105945765736</Timestamp>
      </ProjectDependency>
    </AllDependencies>
    <RootDirectory>
      <Subdirectories>
        <VirtualDirectorySnapshot>
          <Name>USER</Name>
          <Files>
            <VirtualFileSnapshot>
              <RelativePath>..\..\..\Experiment_47_2Serial_IAP_RTC_FLASH_APP\USER\main.c</RelativePath>
            </VirtualFileSnapshot>
            <VirtualFileSnapshot>
              <RelativePath>..\..\..\Experiment_47_2Serial_IAP_RTC_FLASH_APP\USER\stm32f10x_it.c</RelativePath>
            </VirtualFileSnapshot>
            <VirtualFileSnapshot>
              <RelativePath>..\..\..\Experiment_47_2Serial_IAP_RTC_FLASH_APP\USER\system_stm32f10x.c</RelativePath>
            </VirtualFileSnapshot>
          </Files>
        </VirtualDirectorySnapshot>
        <VirtualDirectorySnapshot>
          <Name>HARDWARE</Name>
          <Files>
            <VirtualFileSnapshot>
              <RelativePath>..\..\..\Experiment_47_2Serial_IAP_RTC_FLASH_APP\HARDWARE\LED\led.c</RelativePath>
            </VirtualFileSnapshot>
            <VirtualFileSnapshot>
              <RelativePath>..\..\..\Experiment_47_2Serial_IAP_RTC_FLASH_APP\HARDWARE\KEY\key.c</RelativePath>
            </VirtualFileSnapshot>
            <VirtualFileSnapshot>
              <RelativePath>..\..\..\Experiment_47_2Serial_IAP_RTC_FLASH_APP\HARDWARE\LCD\lcd.c</RelativePath>
            </VirtualFileSnapshot>
            <VirtualFileSnapshot>
              <RelativePath>..\..\..\Experiment_47_2Serial_IAP_RTC_FLASH_APP\HARDWARE\RTC\rtc.c</RelativePath>
            </VirtualFileSnapshot>
          </Files>
        </VirtualDirectorySnapshot>
        <VirtualDirectorySnapshot>
          <Name>SYSTEM</Name>
          <Files>
            <VirtualFileSnapshot>
              <RelativePath>..\..\..\Experiment_47_2Serial_IAP_RTC_FLASH_APP\SYSTEM\delay\delay.c</RelativePath>
            </VirtualFileSnapshot>
            <VirtualFileSnapshot>
              <RelativePath>..\..\..\Experiment_47_2Serial_IAP_RTC_FLASH_APP\SYSTEM\sys\sys.c</RelativePath>
            </VirtualFileSnapshot>
            <VirtualFileSnapshot>
              <RelativePath>..\..\..\Experiment_47_2Serial_IAP_RTC_FLASH_APP\SYSTEM\usart\usart.c</RelativePath>
            </VirtualFileSnapshot>
          </Files>
        </VirtualDirectorySnapshot>
        <VirtualDirectorySnapshot>
          <Name>CORE</Name>
          <Files>
            <VirtualFileSnapshot>
              <RelativePath>..\..\..\Experiment_47_2Serial_IAP_RTC_FLASH_APP\CORE\core_cm3.c</RelativePath>
            </VirtualFileSnapshot>
          </Files>
        </VirtualDirectorySnapshot>
        <VirtualDirectorySnapshot>
          <Name>FWLib</Name>
          <Files>
            <VirtualFileSnapshot>
              <RelativePath>..\..\..\Experiment_47_2Serial_IAP_RTC_FLASH_APP\STM32F10x_FWLib\src\misc.c</RelativePath>
            </VirtualFileSnapshot>
            <VirtualFileSnapshot>
              <RelativePath>..\..\..\Experiment_47_2Serial_IAP_RTC_FLASH_APP\STM32F10x_FWLib\src\stm32f10x_bkp.c</RelativePath>
            </VirtualFileSnapshot>
            <VirtualFileSnapshot>
              <RelativePath>..\..\..\Experiment_47_2Serial_IAP_RTC_FLASH_APP\STM32F10x_FWLib\src\stm32f10x_fsmc.c</RelativePath>
            </VirtualFileSnapshot>
            <VirtualFileSnapshot>
              <RelativePath>..\..\..\Experiment_47_2Serial_IAP_RTC_FLASH_APP\STM32F10x_FWLib\src\stm32f10x_gpio.c</RelativePath>
            </VirtualFileSnapshot>
            <VirtualFileSnapshot>
              <RelativePath>..\..\..\Experiment_47_2Serial_IAP_RTC_FLASH_APP\STM32F10x_FWLib\src\stm32f10x_pwr.c</RelativePath>
            </VirtualFileSnapshot>
            <VirtualFileSnapshot>
              <RelativePath>..\..\..\Experiment_47_2Serial_IAP_RTC_FLASH_APP\STM32F10x_FWLib\src\stm32f10x_rcc.c</RelativePath>
            </VirtualFileSnapshot>
            <VirtualFileSnapshot>
              <RelativePath>..\..\..\Experiment_47_2Serial_IAP_RTC_FLASH_APP\STM32F10x_FWLib\src\stm32f10x_usart.c</RelativePath>
            </VirtualFileSnapshot>
            <VirtualFileSnapshot>
              <RelativePath>..\..\..\Experiment_47_2Serial_IAP_RTC_FLASH_APP\STM32F10x_FWLib\src\stm32f10x_rtc.c</RelativePath>
            </VirtualFileSnapshot>
            <VirtualFileSnapshot>
              <RelativePath>..\..\..\Experiment_47_2Serial_IAP_RTC_FLASH_APP\STM32F10x_FWLib\src\stm32f10x_tim.c</RelativePath>
            </VirtualFileSnapshot>
          </Files>
        </VirtualDirectorySnapshot>
        <VirtualDirectorySnapshot>
          <Name>USMART</Name>
          <Files>
            <VirtualFileSnapshot>
              <RelativePath>..\..\..\Experiment_47_2Serial_IAP_RTC_FLASH_APP\USMART\usmart.c</RelativePath>
            </VirtualFileSnapshot>
            <VirtualFileSnapshot>
              <RelativePath>..\..\..\Experiment_47_2Serial_IAP_RTC_FLASH_APP\USMART\usmart_config.c</RelativePath>
            </VirtualFileSnapshot>
            <VirtualFileSnapshot>
              <RelativePath>..\..\..\Experiment_47_2Serial_IAP_RTC_FLASH_APP\USMART\usmart_str.c</RelativePath>
            </VirtualFileSnapshot>
          </Files>
        </VirtualDirectorySnapshot>
      </Subdirectories>
      <Files />
    </RootDirectory>
    <Configurations>
      <ImportedConfiguration>
        <Settings>
          <IncludeDirectories>
            <string>E:\VS_GDB\ARM\STM32F103StandardRoutine\Experiment_47_Serial_IAP\Experiment_47_2Serial_IAP_RTC_FLASH_APP\HARDWARE\LED</string>
            <string>E:\VS_GDB\ARM\STM32F103StandardRoutine\Experiment_47_Serial_IAP\Experiment_47_2Serial_IAP_RTC_FLASH_APP\SYSTEM\delay</string>
            <string>E:\VS_GDB\ARM\STM32F103StandardRoutine\Experiment_47_Serial_IAP\Experiment_47_2Serial_IAP_RTC_FLASH_APP\SYSTEM\sys</string>
            <string>E:\VS_GDB\ARM\STM32F103StandardRoutine\Experiment_47_Serial_IAP\Experiment_47_2Serial_IAP_RTC_FLASH_APP\SYSTEM\usart</string>
            <string>E:\VS_GDB\ARM\STM32F103StandardRoutine\Experiment_47_Serial_IAP\Experiment_47_2Serial_IAP_RTC_FLASH_APP\USER</string>
            <string>E:\VS_GDB\ARM\STM32F103StandardRoutine\Experiment_47_Serial_IAP\Experiment_47_2Serial_IAP_RTC_FLASH_APP\STM32F10x_FWLib\inc</string>
            <string>E:\VS_GDB\ARM\STM32F103StandardRoutine\Experiment_47_Serial_IAP\Experiment_47_2Serial_IAP_RTC_FLASH_APP\CORE</string>
            <string>E:\VS_GDB\ARM\STM32F103StandardRoutine\Experiment_47_Serial_IAP\Experiment_47_2Serial_IAP_RTC_FLASH_APP\HARDWARE\KEY</string>
            <string>E:\VS_GDB\ARM\STM32F103StandardRoutine\Experiment_47_Serial_IAP\Experiment_47_2Serial_IAP_RTC_FLASH_APP\HARDWARE\LCD</string>
            <string>E:\VS_GDB\ARM\STM32F103StandardRoutine\Experiment_47_Serial_IAP\Experiment_47_2Serial_IAP_RTC_FLASH_APP\HARDWARE\RTC</string>
            <string>E:\VS_GDB\ARM\STM32F103StandardRoutine\Experiment_47_Serial_IAP\Experiment_47_2Serial_IAP_RTC_FLASH_APP\HARDWARE\RTC</string>
            <string>E:\VS_GDB\ARM\STM32F103StandardRoutine\Experiment_47_Serial_IAP\Experiment_47_2Serial_IAP_RTC_FLASH_APP\USMART</string>
          </IncludeDirectories>
          <PreprocessorMacros>
            <string>$$com.sysprogs.bspoptions.primary_memory$$_layout</string>
            <string>STM32F10X_HD</string>
            <string>USE_STDPERIPH_DRIVER</string>
          </PreprocessorMacros>
          <GeneratePreprocessorOutput>false</GeneratePreprocessorOutput>
          <IsDebugConfiguration>false</IsDebugConfiguration>
        </Settings>
      </ImportedConfiguration>
    </Configurations>
  </ImportedProject>
</EmbeddedProfile>